{
  "$schema": "https://json-schema.org/draft/2020-12/schema",
  "type": "object",
  "properties": {
    "sanPham": {
      "type": "array",
      "items": {
        "type": "object",
        "properties": {
          "tenSanPham": {
            "type": "string"
          },
          "giaTien": {
            "type": "number"
          },
          "soLuongTonKho": {
            "type": "integer"
          },
          "danhMucSanPham": {
            "type": "string"
          }
        },
        "required": [
          "tenSanPham",
          "giaTien",
          "soLuongTonKho",
          "danhMucSanPham"
        ]
      }
    }
  },
  "required": [
    "sanPham"
  ]
}